MANIFEST.in
README.rst
index.html
setup.cfg
setup.py
versioneer.py
chatroom/__init__.py
chatroom/_version.py
chatroom/async_client.py
chatroom/client.py
chatroom/server.py
chatroom/utils.py
chatroom/zeroconf_browser.py
chatroom/zeroconf_server.py
test/test_client.py
turing_chatroom_bus.egg-info/PKG-INFO
turing_chatroom_bus.egg-info/SOURCES.txt
turing_chatroom_bus.egg-info/dependency_links.txt
turing_chatroom_bus.egg-info/requires.txt
turing_chatroom_bus.egg-info/top_level.txt